{
  "availableItems": [
    {
      "name": "運動鞋/日規26.5號/黑色",
      "price": 1000,
      "id": "59-2",
      "category": "Shoes",
      "adopter": null
    },
    {
      "name": "運動鞋/日規29號/黑色",
      "price": 800,
      "id": "59-3",
      "category": "Shoes",
      "adopter": null
    },
    {
      "name": "小米行動電源2/銀色/10000mAh",
      "price": 1000,
      "id": "60-2",
      "category": "Miscellaneous",
      "adopter": null
    },
    {
      "name": "金石堂禮券1000元",
      "price": 1000,
      "id": "60-3",
      "category": "Gift Cards",
      "adopter": null
    },
    {
      "name": "金石堂禮券1000元",
      "price": 1000,
      "id": "63-2",
      "category": "Gift Cards",
      "adopter": null
    },
    {
      "name": "金石堂禮券1000元",
      "price": 1000,
      "id": "63-3",
      "category": "Gift Cards",
      "adopter": null
    },
    {
      "name": "金石堂禮券1200元",
      "price": 1200,
      "id": "64-2",
      "category": "Gift Cards",
      "adopter": null
    },
    {
      "name": "金石堂禮券1000元",
      "price": 1000,
      "id": "64-3",
      "category": "Gift Cards",
      "adopter": null
    },
    {
      "name": "金石堂禮券800元",
      "price": 800,
      "id": "64-4",
      "category": "Gift Cards",
      "adopter": null
    },
    {
      "name": "小米手環2/黑色",
      "price": 1000,
      "id": "66-2",
      "category": "Clothing/Accessory",
      "adopter": null
    },
    {
      "name": "金石堂禮券1000元",
      "price": 1000,
      "id": "85-2",
      "category": "Gift Cards",
      "adopter": null
    },
    {
      "name": "金石堂禮券1000元",
      "price": 1000,
      "id": "85-3",
      "category": "Gift Cards",
      "adopter": null
    },
    {
      "name": "誠品禮券1200元",
      "price": 1200,
      "id": "89-2",
      "category": "Gift Cards",
      "adopter": null
    },
    {
      "name": "金石堂禮券1000元",
      "price": 1000,
      "id": "89-3",
      "category": "Gift Cards",
      "adopter": null
    },
    {
      "name": "慢跑鞋/歐規37號/白色 (不要笨重大雙\r)",
      "price": 1000,
      "id": "91-2",
      "category": "Shoes",
      "adopter": null
    },
    {
      "name": "慢跑鞋/歐規43號/黑色",
      "price": 800,
      "id": "91-3",
      "category": "Shoes",
      "adopter": null
    },
    {
      "name": "誠品圖書禮券1000元",
      "price": 1200,
      "id": "92-4",
      "category": "Gift Cards",
      "adopter": null
    },
    {
      "name": "誠品圖書禮券1000元",
      "price": 1000,
      "id": "92-5",
      "category": "Gift Cards",
      "adopter": null
    },
    {
      "name": "誠品圖書禮券800元",
      "price": 800,
      "id": "92-6",
      "category": "Gift Cards",
      "adopter": null
    },
    {
      "name": "誠品圖書禮券600元",
      "price": 600,
      "id": "92-7",
      "category": "Gift Cards",
      "adopter": null
    },
    {
      "name": "誠品圖書禮券1000元",
      "price": 1000,
      "id": "95-2",
      "category": "Gift Cards",
      "adopter": null
    },
    {
      "name": "誠品圖書禮券1000元",
      "price": 1000,
      "id": "95-3",
      "category": "Gift Cards",
      "adopter": null
    },
    {
      "name": "誠品圖書禮券600元",
      "price": 600,
      "id": "95-4",
      "category": "Gift Cards",
      "adopter": null
    },
    {
      "name": "誠品圖書禮券1000元",
      "price": 1000,
      "id": "96-2",
      "category": "Gift Cards",
      "adopter": null
    },
    {
      "name": "誠品圖書禮券1000元",
      "price": 1000,
      "id": "96-3",
      "category": "Gift Cards",
      "adopter": null
    },
    {
      "name": "誠品圖書禮券800元",
      "price": 800,
      "id": "96-4",
      "category": "Gift Cards",
      "adopter": null
    },
    {
      "name": "誠品圖書禮券600元",
      "price": 600,
      "id": "96-5",
      "category": "Gift Cards",
      "adopter": null
    },
    {
      "name": "誠品禮券1200元",
      "price": 1200,
      "id": "102-3",
      "category": "Gift Cards",
      "adopter": null
    },
    {
      "name": "金石堂禮券800元",
      "price": 800,
      "id": "103-2",
      "category": "Gift Cards",
      "adopter": null
    },
    {
      "name": "金石堂禮券800元",
      "price": 800,
      "id": "103-3",
      "category": "Gift Cards",
      "adopter": null
    },
    {
      "name": "運動鞋\\黑色\\日規24.5號",
      "price": 1000,
      "id": "111-2",
      "category": "Shoes",
      "adopter": null
    },
    {
      "name": "運動鞋\\黑色\\日規24號",
      "price": 800,
      "id": "111-3",
      "category": "Shoes",
      "adopter": null
    },
    {
      "name": "誠品禮券1200元",
      "price": 1200,
      "id": "113-2",
      "category": "Gift Cards",
      "adopter": null
    },
    {
      "name": "黑色防水羽絨外套/身高175cm體重70kg/XL號",
      "price": 1200,
      "id": "113-3",
      "category": "Clothing/Accessory",
      "adopter": null
    },
    {
      "name": "誠品禮券1000元",
      "price": 1200,
      "id": "113-4",
      "category": "Gift Cards",
      "adopter": null
    },
    {
      "name": "外套/黑色/男生M號/身高160cm體重49kg",
      "price": 1200,
      "id": "114-3",
      "category": "Clothing/Accessory",
      "adopter": null
    },
    {
      "name": "NARS惹火唇膏/色號:MONA",
      "price": 1200,
      "id": "119-2",
      "category": "Miscellaneous",
      "adopter": null
    },
    {
      "name": "電腦水冷散熱器(電腦散熱器)",
      "price": 1000,
      "id": "119-3",
      "category": "Miscellaneous",
      "adopter": null
    },
    {
      "name": "誠品禮券1200元",
      "price": 1200,
      "id": "124-2",
      "category": "Gift Cards",
      "adopter": null
    },
    {
      "name": "誠品禮券1000元",
      "price": 1000,
      "id": "124-3",
      "category": "Gift Cards",
      "adopter": null
    },
    {
      "name": "金石堂禮券1200元",
      "price": 1200,
      "id": "125-2",
      "category": "Gift Cards",
      "adopter": null
    },
    {
      "name": "金石堂禮券1200元",
      "price": 1200,
      "id": "125-3",
      "category": "Gift Cards",
      "adopter": null
    },
    {
      "name": "籃球鞋/日規28.5號/黑色",
      "price": 800,
      "id": "127-2",
      "category": "Shoes",
      "adopter": null
    },
    {
      "name": "籃球鞋/日規28.5號/白色",
      "price": 800,
      "id": "127-3",
      "category": "Shoes",
      "adopter": null
    },
    {
      "name": "白色球鞋/歐規44號",
      "price": 1000,
      "id": "129-3",
      "category": "Shoes",
      "adopter": null
    },
    {
      "name": "電子手錶/有卡通圖案",
      "price": 1000,
      "id": "129-4",
      "category": "Clothing/Accessory",
      "adopter": null
    },
    {
      "name": "防風羽絨外套/M號/灰色或軍綠色/158cm/48kg",
      "price": 1200,
      "id": "138-2",
      "category": "Clothing/Accessory",
      "adopter": null
    },
    {
      "name": "黑色腰包",
      "price": 1200,
      "id": "138-3",
      "category": "Miscellaneous",
      "adopter": null
    },
    {
      "name": "羽毛球組(含：羽球拍、羽球、羽球袋)",
      "price": 1000,
      "id": "141-2",
      "category": "Miscellaneous",
      "adopter": null
    },
    {
      "name": "運動鞋/歐規37號/黑色",
      "price": 600,
      "id": "141-3",
      "category": "Shoes",
      "adopter": null
    },
    {
      "name": "兒童環保美甲組",
      "price": 600,
      "id": "141-4",
      "category": "Miscellaneous",
      "adopter": null
    },
    {
      "name": "誠品禮券1000元",
      "price": 1000,
      "id": "143-2",
      "category": "Gift Cards",
      "adopter": null
    },
    {
      "name": "誠品禮券1000元",
      "price": 1000,
      "id": "143-3",
      "category": "Gift Cards",
      "adopter": null
    },
    {
      "name": "誠品禮券1200元",
      "price": 1200,
      "id": "146-2",
      "category": "Gift Cards",
      "adopter": null
    },
    {
      "name": "誠品禮券1200元",
      "price": 1200,
      "id": "146-3",
      "category": "Gift Cards",
      "adopter": null
    },
    {
      "name": "誠品禮券600元",
      "price": 600,
      "id": "146-4",
      "category": "Gift Cards",
      "adopter": null
    },
    {
      "name": "運動鞋/日規24號/黑色白底/要有鞋帶",
      "price": 1000,
      "id": "149-3",
      "category": "Shoes",
      "adopter": null
    },
    {
      "name": "拼接腰帶防盜雙肩包/卡其色",
      "price": 1000,
      "id": "149-4",
      "category": "Miscellaneous",
      "adopter": null
    },
    {
      "name": "無線藍芽麥克風/玫瑰金色",
      "price": 800,
      "id": "149-5",
      "category": "Miscellaneous",
      "adopter": null
    },
    {
      "name": "小米手錶/紫色",
      "price": 800,
      "id": "149-6",
      "category": "Clothing/Accessory",
      "adopter": null
    },
    {
      "name": "電子錶/黑色",
      "price": 800,
      "id": "151-2",
      "category": "Clothing/Accessory",
      "adopter": null
    },
    {
      "name": "布鞋/日規23號/黑色",
      "price": 600,
      "id": "151-3",
      "category": "Shoes",
      "adopter": null
    },
    {
      "name": "誠品禮券1000元",
      "price": 1000,
      "id": "153-2",
      "category": "Gift Cards",
      "adopter": null
    },
    {
      "name": "誠品禮券1000元",
      "price": 1000,
      "id": "153-3",
      "category": "Gift Cards",
      "adopter": null
    },
    {
      "name": "誠品禮券600元",
      "price": 600,
      "id": "153-4",
      "category": "Gift Cards",
      "adopter": null
    },
    {
      "name": "誠品禮券1000元",
      "price": 1000,
      "id": "158-2",
      "category": "Gift Cards",
      "adopter": null
    },
    {
      "name": "誠品禮券800元",
      "price": 800,
      "id": "158-3",
      "category": "Gift Cards",
      "adopter": null
    },
    {
      "name": "嬰兒厚外套/童裝5號/藍色/90cm/7kg/男生",
      "price": 600,
      "id": "158-4",
      "category": "Clothing/Accessory",
      "adopter": null
    },
    {
      "name": "室外籃球/尺寸:7號",
      "price": 1000,
      "id": "160-4",
      "category": "Miscellaneous",
      "adopter": null
    },
    {
      "name": "電子錶/黑色",
      "price": 600,
      "id": "163-3",
      "category": "Clothing/Accessory",
      "adopter": null
    },
    {
      "name": "電子錶/藍色",
      "price": 600,
      "id": "163-4",
      "category": "Clothing/Accessory",
      "adopter": null
    },
    {
      "name": "布鞋/日規24.5號/白色",
      "price": 1000,
      "id": "164-3",
      "category": "Shoes",
      "adopter": null
    },
    {
      "name": "薄外套/L/黑色/170cm/68kg",
      "price": 800,
      "id": "164-4",
      "category": "Clothing/Accessory",
      "adopter": null
    },
    {
      "name": "無線藍芽耳機",
      "price": 1000,
      "id": "168-2",
      "category": "Miscellaneous",
      "adopter": null
    },
    {
      "name": "無線藍芽耳機",
      "price": 1000,
      "id": "168-3",
      "category": "Miscellaneous",
      "adopter": null
    },
    {
      "name": "無線藍芽耳機",
      "price": 800,
      "id": "168-4",
      "category": "Miscellaneous",
      "adopter": null
    },
    {
      "name": "電子錶/藍色/角落生物圖案",
      "price": 600,
      "id": "168-5",
      "category": "Clothing/Accessory",
      "adopter": null
    },
    {
      "name": "誠品禮券1000元",
      "price": 1000,
      "id": "171-2",
      "category": "Gift Cards",
      "adopter": null
    },
    {
      "name": "誠品禮券800元",
      "price": 800,
      "id": "171-3",
      "category": "Gift Cards",
      "adopter": null
    },
    {
      "name": "誠品禮券800元",
      "price": 800,
      "id": "171-4",
      "category": "Gift Cards",
      "adopter": null
    },
    {
      "name": "誠品禮券600元",
      "price": 600,
      "id": "171-5",
      "category": "Gift Cards",
      "adopter": null
    },
    {
      "name": "誠品禮券1200元",
      "price": 1200,
      "id": "172-2",
      "category": "Gift Cards",
      "adopter": null
    },
    {
      "name": "誠品禮券1000元",
      "price": 1000,
      "id": "172-3",
      "category": "Gift Cards",
      "adopter": null
    },
    {
      "name": "鞋子/歐規40號/藍色",
      "price": 1000,
      "id": "174-2",
      "category": "Shoes",
      "adopter": null
    },
    {
      "name": "鞋子/日規24號/藍色",
      "price": 800,
      "id": "174-3",
      "category": "Shoes",
      "adopter": null
    },
    {
      "name": "鞋子/日規16號/藍色",
      "price": 600,
      "id": "174-4",
      "category": "Shoes",
      "adopter": null
    },
    {
      "name": "誠品禮券800元",
      "price": 800,
      "id": "176-1",
      "category": "Gift Cards",
      "adopter": null
    },
    {
      "name": "金石堂1200元",
      "price": 1200,
      "id": "179-3",
      "category": "Gift Cards",
      "adopter": null
    },
    {
      "name": "後背包/黑色/容量大的",
      "price": 1200,
      "id": "186-2",
      "category": "Miscellaneous",
      "adopter": null
    },
    {
      "name": "誠品禮券1200元",
      "price": 1200,
      "id": "189-2",
      "category": "Gift Cards",
      "adopter": null
    },
    {
      "name": "誠品禮券1200元",
      "price": 1200,
      "id": "189-3",
      "category": "Gift Cards",
      "adopter": null
    },
    {
      "name": "運動鞋/日規26.5號/黑色",
      "price": 1000,
      "id": "193-2",
      "category": "Shoes",
      "adopter": null
    },
    {
      "name": "運動鞋/日規26.5號/藍色",
      "price": 800,
      "id": "193-3",
      "category": "Shoes",
      "adopter": null
    },
    {
      "name": "運動鞋/日規20號/紅色",
      "price": 600,
      "id": "193-4",
      "category": "Shoes",
      "adopter": null
    },
    {
      "name": "保暖外套/XL號/160cm/75kg",
      "price": 1000,
      "id": "194-2",
      "category": "Clothing/Accessory",
      "adopter": null
    },
    {
      "name": "籃球鞋/日規25號/黑色或白色",
      "price": 1200,
      "id": "204-1",
      "category": "Shoes",
      "adopter": null
    },
    {
      "name": "金石堂禮券1200元",
      "price": 1200,
      "id": "210-1",
      "category": "Gift Cards",
      "adopter": null
    },
    {
      "name": "金石堂禮券1000元",
      "price": 1000,
      "id": "210-2",
      "category": "Gift Cards",
      "adopter": null
    },
    {
      "name": "金石堂禮券1000元",
      "price": 1000,
      "id": "210-3",
      "category": "Gift Cards",
      "adopter": null
    },
    {
      "name": "黑色鞋子/日規24號",
      "price": 800,
      "id": "213-1",
      "category": "Shoes",
      "adopter": null
    },
    {
      "name": "背包式書包/粉紅色",
      "price": 600,
      "id": "213-2",
      "category": "Miscellaneous",
      "adopter": null
    },
    {
      "name": "金石堂禮券1000元",
      "price": 1000,
      "id": "215-1",
      "category": "Gift Cards",
      "adopter": null
    },
    {
      "name": "金石堂禮券800元",
      "price": 800,
      "id": "215-2",
      "category": "Gift Cards",
      "adopter": null
    },
    {
      "name": "芭比娃娃套組",
      "price": 600,
      "id": "215-3",
      "category": "Miscellaneous",
      "adopter": null
    },
    {
      "name": "金石堂禮券1000元",
      "price": 1000,
      "id": "216-1",
      "category": "Gift Cards",
      "adopter": null
    },
    {
      "name": "黑色手錶(指針型)",
      "price": 1000,
      "id": "217-1",
      "category": "Clothing/Accessory",
      "adopter": null
    },
    {
      "name": "慢跑鞋/日規24號/黑或白",
      "price": 800,
      "id": "217-2",
      "category": "Shoes",
      "adopter": null
    },
    {
      "name": "布鞋/日規24號/黑色",
      "price": 600,
      "id": "217-3",
      "category": "Shoes",
      "adopter": null
    },
    {
      "name": "羽絨外套/L號/紅色/157cm/54kg",
      "price": 800,
      "id": "218-1",
      "category": "Clothing/Accessory",
      "adopter": null
    },
    {
      "name": "誠品1200元",
      "price": 1200,
      "id": "224-1",
      "category": "Gift Cards",
      "adopter": null
    },
    {
      "name": "籃球鞋/日規27.5號/黑色",
      "price": 1000,
      "id": "224-2",
      "category": "Shoes",
      "adopter": null
    },
    {
      "name": "運動鞋/27號/黑色為主色/藍色為配色",
      "price": 1200,
      "id": "228-1",
      "category": "Shoes",
      "adopter": null
    },
    {
      "name": "布鞋/歐規43號/黑色",
      "price": 800,
      "id": "230-1",
      "category": "Shoes",
      "adopter": null
    },
    {
      "name": "布鞋/歐規42號/黑色 (腳背很厚\r)",
      "price": 800,
      "id": "230-2",
      "category": "Shoes",
      "adopter": null
    },
    {
      "name": "金石堂禮券1200元",
      "price": 1200,
      "id": "231-1",
      "category": "Gift Cards",
      "adopter": null
    },
    {
      "name": "運動鞋/歐規37號/不要白色 (魔鬼沾黏貼式，不要鞋帶的\r)",
      "price": 1000,
      "id": "231-2",
      "category": "Shoes",
      "adopter": null
    },
    {
      "name": "金石堂禮券1000元",
      "price": 1000,
      "id": "233-1",
      "category": "Gift Cards",
      "adopter": null
    },
    {
      "name": "手錶(指針式)/紅色",
      "price": 800,
      "id": "233-2",
      "category": "Clothing/Accessory",
      "adopter": null
    },
    {
      "name": "手錶(指針式)/黑色",
      "price": 800,
      "id": "233-3",
      "category": "Clothing/Accessory",
      "adopter": null
    },
    {
      "name": "金石堂禮券600元",
      "price": 600,
      "id": "234-2",
      "category": "Gift Cards",
      "adopter": null
    },
    {
      "name": "誠品禮券1000元",
      "price": 1000,
      "id": "236-1",
      "category": "Gift Cards",
      "adopter": null
    },
    {
      "name": "誠品禮券800元",
      "price": 800,
      "id": "236-2",
      "category": "Gift Cards",
      "adopter": null
    },
    {
      "name": "誠品禮券1000元",
      "price": 1000,
      "id": "238-1",
      "category": "Gift Cards",
      "adopter": null
    },
    {
      "name": "誠品禮券600元",
      "price": 600,
      "id": "238-2",
      "category": "Gift Cards",
      "adopter": null
    },
    {
      "name": "布鞋/日規26號/黑色",
      "price": 800,
      "id": "240-2",
      "category": "Shoes",
      "adopter": null
    },
    {
      "name": "粉紅色後背包/不要有圖案，素面即可 (很多拉鍊、口袋，可帶出去玩\r)",
      "price": 800,
      "id": "241-1",
      "category": "Miscellaneous",
      "adopter": null
    },
    {
      "name": "黑色後背包/不要有圖案，素面即可 (很多拉鍊、口袋，可帶出去玩\r)",
      "price": 600,
      "id": "241-2",
      "category": "Miscellaneous",
      "adopter": null
    },
    {
      "name": "鞋子/日規25號/黑白",
      "price": 800,
      "id": "243-1",
      "category": "Shoes",
      "adopter": null
    },
    {
      "name": "鞋子/日規25號/黑粉紅",
      "price": 600,
      "id": "243-2",
      "category": "Shoes",
      "adopter": null
    },
    {
      "name": "鞋子/日規23號/粉紅",
      "price": 600,
      "id": "243-3",
      "category": "Shoes",
      "adopter": null
    },
    {
      "name": "金石堂禮券1200元",
      "price": 1200,
      "id": "248-1",
      "category": "Gift Cards",
      "adopter": null
    },
    {
      "name": "金石堂禮券1000元",
      "price": 1000,
      "id": "248-2",
      "category": "Gift Cards",
      "adopter": null
    },
    {
      "name": "金石堂禮券800元",
      "price": 800,
      "id": "248-3",
      "category": "Gift Cards",
      "adopter": null
    },
    {
      "name": "誠品禮券800元",
      "price": 800,
      "id": "250-1",
      "category": "Gift Cards",
      "adopter": null
    },
    {
      "name": "誠品禮券1200元",
      "price": 1200,
      "id": "252-1",
      "category": "Gift Cards",
      "adopter": null
    },
    {
      "name": "籃球",
      "price": 800,
      "id": "252-2",
      "category": "Miscellaneous",
      "adopter": null
    },
    {
      "name": "誠品禮卷1000元",
      "price": 1000,
      "id": "253-1",
      "category": "Gift Cards",
      "adopter": null
    },
    {
      "name": "誠品禮券600元",
      "price": 600,
      "id": "253-2",
      "category": "Gift Cards",
      "adopter": null
    },
    {
      "name": "運動鞋/日規23.5號 (底軟舒適\r)",
      "price": 600,
      "id": "255-1",
      "category": "Shoes",
      "adopter": null
    },
    {
      "name": "布鞋/歐規36號/黑色",
      "price": 600,
      "id": "261-1",
      "category": "Shoes",
      "adopter": null
    },
    {
      "name": "布鞋/歐規34號/白色",
      "price": 600,
      "id": "261-2",
      "category": "Shoes",
      "adopter": null
    },
    {
      "name": "金石堂禮券800元",
      "price": 600,
      "id": "262-1",
      "category": "Gift Cards",
      "adopter": null
    },
    {
      "name": "迪卡農極佳手感5號籃球(TARMAK 700)",
      "price": 600,
      "id": "262-2",
      "category": "Miscellaneous",
      "adopter": null
    },
    {
      "name": "金石堂禮券600元",
      "price": 600,
      "id": "263-1",
      "category": "Gift Cards",
      "adopter": null
    },
    {
      "name": "誠品禮券1000元",
      "price": 1000,
      "id": "266-2",
      "category": "Gift Cards",
      "adopter": null
    },
    {
      "name": "誠品禮券1000元",
      "price": 1000,
      "id": "266-1",
      "category": "Gift Cards",
      "adopter": null
    },
    {
      "name": "行動電源",
      "price": 1200,
      "id": "267-1",
      "category": "Miscellaneous",
      "adopter": null
    },
    {
      "name": "金石堂禮券1000元",
      "price": 1000,
      "id": "267-2",
      "category": "Gift Cards",
      "adopter": null
    },
    {
      "name": "金石堂禮券1000元",
      "price": 1000,
      "id": "267-3",
      "category": "Gift Cards",
      "adopter": null
    },
    {
      "name": "紅色羽絨外套/身高150cm/體重34kg",
      "price": 600,
      "id": "268-1",
      "category": "Clothing/Accessory",
      "adopter": null
    },
    {
      "name": "冬天外套/XL號/藍色/170cm60kg",
      "price": 1000,
      "id": "269-1",
      "category": "Clothing/Accessory",
      "adopter": null
    },
    {
      "name": "扯鈴",
      "price": 600,
      "id": "269-2",
      "category": "Miscellaneous",
      "adopter": null
    },
    {
      "name": "運動鞋/日規23/黑色",
      "price": 600,
      "id": "269-3",
      "category": "Shoes",
      "adopter": null
    },
    {
      "name": "後背包/黑色",
      "price": 1200,
      "id": "270-1",
      "category": "Miscellaneous",
      "adopter": null
    },
    {
      "name": "文具組",
      "price": 800,
      "id": "270-2",
      "category": "Stationery",
      "adopter": null
    },
    {
      "name": "禮券1200元",
      "price": 1200,
      "id": "274-1",
      "category": "Gift Cards",
      "adopter": null
    },
    {
      "name": "禮券1000元",
      "price": 1000,
      "id": "274-2",
      "category": "Gift Cards",
      "adopter": null
    },
    {
      "name": "電動火車玩具",
      "price": 600,
      "id": "275-1",
      "category": "Miscellaneous",
      "adopter": null
    },
    {
      "name": "hello kitty 列車(火車或汽車)",
      "price": 600,
      "id": "275-2",
      "category": "Miscellaneous",
      "adopter": null
    },
    {
      "name": "籃球鞋/日規23.5號/黑色",
      "price": 600,
      "id": "276-1",
      "category": "Shoes",
      "adopter": null
    },
    {
      "name": "羽毛球拍(一組兩支)",
      "price": 800,
      "id": "276-2",
      "category": "Miscellaneous",
      "adopter": null
    },
    {
      "name": "運動鞋/日規25號/可愛圖案",
      "price": 600,
      "id": "278-1",
      "category": "Shoes",
      "adopter": null
    },
    {
      "name": "運動鞋/日規21號/可愛圖案",
      "price": 600,
      "id": "278-2",
      "category": "Shoes",
      "adopter": null
    },
    {
      "name": "運動鞋/日規21號/可愛圖案",
      "price": 600,
      "id": "278-3",
      "category": "Shoes",
      "adopter": null
    },
    {
      "name": "運動鞋/日規23號/藍或白色",
      "price": 600,
      "id": "280-1",
      "category": "Shoes",
      "adopter": null
    },
    {
      "name": "運動鞋/日規22號/藍或白色",
      "price": 600,
      "id": "280-2",
      "category": "Shoes",
      "adopter": null
    },
    {
      "name": "T-SHIRT(短袖)/男性L號/藍色",
      "price": 1000,
      "id": "281-1",
      "category": "Clothing/Accessory",
      "adopter": null
    },
    {
      "name": "防水手錶/藍色",
      "price": 600,
      "id": "281-2",
      "category": "Clothing/Accessory",
      "adopter": null
    },
    {
      "name": "戰鬥陀螺正式版/血神槍(陀螺名稱)",
      "price": 600,
      "id": "281-3",
      "category": "Miscellaneous",
      "adopter": null
    },
    {
      "name": "羽絨外套/XL號/粉紅色/無圖案、女款",
      "price": 800,
      "id": "282-1",
      "category": "Clothing/Accessory",
      "adopter": null
    },
    {
      "name": "黑色手錶",
      "price": 800,
      "id": "283-1",
      "category": "Clothing/Accessory",
      "adopter": null
    },
    {
      "name": "短袖上衣/男性L號/黑色/T-shirt",
      "price": 800,
      "id": "284-1",
      "category": "Clothing/Accessory",
      "adopter": null
    },
    {
      "name": "金石堂禮卷800元",
      "price": 800,
      "id": "286-1",
      "category": "Gift Cards",
      "adopter": null
    },
    {
      "name": "慢跑鞋/歐規40號/黑色",
      "price": 1200,
      "id": "287-1",
      "category": "Shoes",
      "adopter": null
    },
    {
      "name": "慢跑鞋/歐規37號/黑色",
      "price": 800,
      "id": "287-2",
      "category": "Shoes",
      "adopter": null
    },
    {
      "name": "慢跑鞋/歐規37號/黑色",
      "price": 600,
      "id": "287-3",
      "category": "Shoes",
      "adopter": null
    },
    {
      "name": "MP4隨身聽",
      "price": 600,
      "id": "287-4",
      "category": "Miscellaneous",
      "adopter": null
    },
    {
      "name": "運動鞋/歐規36號/粉紅色",
      "price": 600,
      "id": "289-1",
      "category": "Shoes",
      "adopter": null
    },
    {
      "name": "羽毛球拍組",
      "price": 600,
      "id": "289-2",
      "category": "Miscellaneous",
      "adopter": null
    },
    {
      "name": "玩具挖土機",
      "price": 600,
      "id": "289-3",
      "category": "Miscellaneous",
      "adopter": null
    },
    {
      "name": "魔鬼沾黏式布鞋/紫色/日規24號",
      "price": 600,
      "id": "290-1",
      "category": "Shoes",
      "adopter": null
    },
    {
      "name": "玩具挖土機或玩具吊車",
      "price": 600,
      "id": "290-2",
      "category": "Miscellaneous",
      "adopter": null
    },
    {
      "name": "誠品禮券1200元",
      "price": 1200,
      "id": "291-1",
      "category": "Gift Cards",
      "adopter": null
    },
    {
      "name": "誠品禮券1000元",
      "price": 1000,
      "id": "291-2",
      "category": "Gift Cards",
      "adopter": null
    },
    {
      "name": "誠品禮券800元",
      "price": 800,
      "id": "291-3",
      "category": "Gift Cards",
      "adopter": null
    },
    {
      "name": "運動鞋/歐規41號/黑色",
      "price": 1000,
      "id": "293-1",
      "category": "Shoes",
      "adopter": null
    },
    {
      "name": "誠品禮券1000元",
      "price": 1000,
      "id": "293-2",
      "category": "Gift Cards",
      "adopter": null
    },
    {
      "name": "誠品禮券800元",
      "price": 800,
      "id": "295-1",
      "category": "Gift Cards",
      "adopter": null
    },
    {
      "name": "防水100m電子錶/綠色",
      "price": 600,
      "id": "295-2",
      "category": "Clothing/Accessory",
      "adopter": null
    },
    {
      "name": "玩具-強襲者連飛衝鋒槍 (NERF\r)",
      "price": 600,
      "id": "295-3",
      "category": "Miscellaneous",
      "adopter": null
    },
    {
      "name": "誠品禮券1000元",
      "price": 1000,
      "id": "296-1",
      "category": "Gift Cards",
      "adopter": null
    },
    {
      "name": "誠品禮券800元",
      "price": 800,
      "id": "296-2",
      "category": "Gift Cards",
      "adopter": null
    },
    {
      "name": "誠品禮券600元",
      "price": 600,
      "id": "296-3",
      "category": "Gift Cards",
      "adopter": null
    },
    {
      "name": "誠品禮券600元",
      "price": 600,
      "id": "299-1",
      "category": "Gift Cards",
      "adopter": null
    },
    {
      "name": "藍色外套/M號",
      "price": 600,
      "id": "301-1",
      "category": "Clothing/Accessory",
      "adopter": null
    },
    {
      "name": "紅色外套/M號",
      "price": 600,
      "id": "301-2",
      "category": "Clothing/Accessory",
      "adopter": null
    },
    {
      "name": "誠品禮卷800元",
      "price": 800,
      "id": "302-1",
      "category": "Gift Cards",
      "adopter": null
    },
    {
      "name": "封蠟章組合",
      "price": 800,
      "id": "302-2",
      "category": "Miscellaneous",
      "adopter": null
    },
    {
      "name": "故事機",
      "price": 600,
      "id": "303-1",
      "category": "Miscellaneous",
      "adopter": null
    },
    {
      "name": "禮券1000元",
      "price": 1000,
      "id": "304-1",
      "category": "Gift Cards",
      "adopter": null
    },
    {
      "name": "禮券1000元",
      "price": 1000,
      "id": "304-2",
      "category": "Gift Cards",
      "adopter": null
    },
    {
      "name": "運動鞋/日規21號/粉紫色/綁鞋帶樣式",
      "price": 600,
      "id": "305-1",
      "category": "Shoes",
      "adopter": null
    },
    {
      "name": "運動鞋/日規18號/綠色/魔鬼沾樣式",
      "price": 600,
      "id": "305-2",
      "category": "Shoes",
      "adopter": null
    },
    {
      "name": "運動鞋/日規18號/淺藍色/魔鬼沾樣式",
      "price": 600,
      "id": "305-3",
      "category": "Shoes",
      "adopter": null
    },
    {
      "name": "運動鞋/日規18號/粉紅色/魔鬼沾樣式",
      "price": 600,
      "id": "305-4",
      "category": "Shoes",
      "adopter": null
    },
    {
      "name": "連帽外套/女性L號/黑色/156cm/55kg",
      "price": 800,
      "id": "306-1",
      "category": "Clothing/Accessory",
      "adopter": null
    },
    {
      "name": "連帽外套/男性M號/藍色/135cm/30kg",
      "price": 600,
      "id": "306-2",
      "category": "Clothing/Accessory",
      "adopter": null
    },
    {
      "name": "厚的長版外套/L號/黑色/175cm67kg",
      "price": 1000,
      "id": "307-1",
      "category": "Clothing/Accessory",
      "adopter": null
    },
    {
      "name": "潮TT-shirt/L號/黃色/170cm56kg",
      "price": 1000,
      "id": "307-2",
      "category": "Clothing/Accessory",
      "adopter": null
    },
    {
      "name": "可愛的小背包",
      "price": 600,
      "id": "307-3",
      "category": "Miscellaneous",
      "adopter": null
    },
    {
      "name": "籃球/尺寸:七號/咖啡色/隨機圖案",
      "price": 800,
      "id": "308-1",
      "category": "Miscellaneous",
      "adopter": null
    },
    {
      "name": "誠品禮券800元",
      "price": 800,
      "id": "310-1",
      "category": "Gift Cards",
      "adopter": null
    },
    {
      "name": "誠品禮券600元",
      "price": 600,
      "id": "310-2",
      "category": "Gift Cards",
      "adopter": null
    },
    {
      "name": "彩色筆組合",
      "price": 600,
      "id": "310-3",
      "category": "Stationery",
      "adopter": null
    },
    {
      "name": "手錶/白色/愛心、HELLO KITTY 圖案",
      "price": 600,
      "id": "313-1",
      "category": "Clothing/Accessory",
      "adopter": null
    },
    {
      "name": "運動鞋/歐規41.5號/黑色",
      "price": 800,
      "id": "314-1",
      "category": "Shoes",
      "adopter": null
    },
    {
      "name": "誠品禮券1200元",
      "price": 1200,
      "id": "317-1",
      "category": "Gift Cards",
      "adopter": null
    },
    {
      "name": "籃球/尺寸:七號/橘色或咖啡色/無圖案",
      "price": 800,
      "id": "317-2",
      "category": "Miscellaneous",
      "adopter": null
    },
    {
      "name": "金石堂禮券800元",
      "price": 800,
      "id": "320-1",
      "category": "Gift Cards",
      "adopter": null
    },
    {
      "name": "金石堂禮券600元",
      "price": 600,
      "id": "320-2",
      "category": "Gift Cards",
      "adopter": null
    },
    {
      "name": "誠品禮券600元",
      "price": 600,
      "id": "321-1",
      "category": "Gift Cards",
      "adopter": null
    },
    {
      "name": "誠品禮券600元",
      "price": 600,
      "id": "321-2",
      "category": "Gift Cards",
      "adopter": null
    },
    {
      "name": "金石堂禮券800元",
      "price": 800,
      "id": "324-1",
      "category": "Gift Cards",
      "adopter": null
    },
    {
      "name": "誠品禮券800元",
      "price": 800,
      "id": "325-1",
      "category": "Gift Cards",
      "adopter": null
    },
    {
      "name": "火車軌道組玩具",
      "price": 600,
      "id": "325-2",
      "category": "Miscellaneous",
      "adopter": null
    },
    {
      "name": "運動鞋/歐規42號/黑色",
      "price": 600,
      "id": "326-1",
      "category": "Shoes",
      "adopter": null
    },
    {
      "name": "運動鞋/歐規32號/黑色",
      "price": 600,
      "id": "326-2",
      "category": "Shoes",
      "adopter": null
    },
    {
      "name": "運動鞋/歐規29號/黑色",
      "price": 600,
      "id": "326-3",
      "category": "Shoes",
      "adopter": null
    },
    {
      "name": "誠品禮券800元",
      "price": 800,
      "id": "327-1",
      "category": "Gift Cards",
      "adopter": null
    },
    {
      "name": "誠品禮券600元",
      "price": 600,
      "id": "327-2",
      "category": "Gift Cards",
      "adopter": null
    },
    {
      "name": "誠品禮券600元",
      "price": 600,
      "id": "327-3",
      "category": "Gift Cards",
      "adopter": null
    },
    {
      "name": "誠品禮券600元 (購買嬰兒圖書或玩具用\r)",
      "price": 600,
      "id": "327-4",
      "category": "Gift Cards",
      "adopter": null
    },
    {
      "name": "誠品禮券600元",
      "price": 600,
      "id": "328-1",
      "category": "Gift Cards",
      "adopter": null
    },
    {
      "name": "繪圖用麥克筆組合",
      "price": 800,
      "id": "329-1",
      "category": "Stationery",
      "adopter": null
    },
    {
      "name": "玩具--光劍",
      "price": 600,
      "id": "329-2",
      "category": "Miscellaneous",
      "adopter": null
    },
    {
      "name": "粉紅色書包/L號",
      "price": 600,
      "id": "331-1",
      "category": "Miscellaneous",
      "adopter": null
    },
    {
      "name": "衣服/兒童18號或L號/白色  (身高120cm25kg)",
      "price": 600,
      "id": "333-1",
      "category": "Clothing/Accessory",
      "adopter": null
    },
    {
      "name": "電子錶/紅色",
      "price": 600,
      "id": "334-1",
      "category": "Clothing/Accessory",
      "adopter": null
    },
    {
      "name": "電子錶/粉紅色",
      "price": 600,
      "id": "334-2",
      "category": "Clothing/Accessory",
      "adopter": null
    },
    {
      "name": "誠品禮券600元",
      "price": 600,
      "id": "335-1",
      "category": "Gift Cards",
      "adopter": null
    },
    {
      "name": "誠品禮券1000元",
      "price": 1000,
      "id": "336-1",
      "category": "Gift Cards",
      "adopter": null
    },
    {
      "name": "運動鞋/日規21號/粉紅色/Kitty貓",
      "price": 600,
      "id": "336-2",
      "category": "Shoes",
      "adopter": null
    },
    {
      "name": "金石堂禮卷600元",
      "price": 600,
      "id": "338-1",
      "category": "Gift Cards",
      "adopter": null
    },
    {
      "name": "手錶(指針式)/紅色",
      "price": 600,
      "id": "339-1",
      "category": "Clothing/Accessory",
      "adopter": null
    },
    {
      "name": "手錶(指針式)/藍色",
      "price": 600,
      "id": "339-2",
      "category": "Clothing/Accessory",
      "adopter": null
    },
    {
      "name": "運動手錶(可計時) (不要幼稚的樣式\r)",
      "price": 800,
      "id": "340-1",
      "category": "Clothing/Accessory",
      "adopter": null
    },
    {
      "name": "佩佩豬文具組",
      "price": 600,
      "id": "342-1",
      "category": "Stationery",
      "adopter": null
    },
    {
      "name": "家人同樂桌遊",
      "price": 600,
      "id": "342-2",
      "category": "Miscellaneous",
      "adopter": null
    },
    {
      "name": "籃球鞋/日規25號/藍色",
      "price": 600,
      "id": "343-1",
      "category": "Shoes",
      "adopter": null
    },
    {
      "name": "家人同樂桌遊",
      "price": 600,
      "id": "344-1",
      "category": "Miscellaneous",
      "adopter": null
    },
    {
      "name": "運動鞋/日規26.5號/藍色",
      "price": 1200,
      "id": "346-1",
      "category": "Shoes",
      "adopter": null
    },
    {
      "name": "運動鞋/日規24號/藍色",
      "price": 600,
      "id": "346-2",
      "category": "Shoes",
      "adopter": null
    },
    {
      "name": "三國志(呂布)公仔模型",
      "price": 600,
      "id": "347-1",
      "category": "Miscellaneous",
      "adopter": null
    },
    {
      "name": "書包/紅色",
      "price": 600,
      "id": "349-1",
      "category": "Miscellaneous",
      "adopter": null
    },
    {
      "name": "書包/綠色/不要動漫圖案",
      "price": 600,
      "id": "351-1",
      "category": "Miscellaneous",
      "adopter": null
    },
    {
      "name": "黑色後背包，不要有圖案",
      "price": 800,
      "id": "358-2",
      "category": "Miscellaneous",
      "adopter": null
    },
    {
      "name": "運動鞋/歐規35號/紅色",
      "price": 600,
      "id": "360-1",
      "category": "Shoes",
      "adopter": null
    },
    {
      "name": "運動鞋/歐規34號/粉紅色",
      "price": 600,
      "id": "360-2",
      "category": "Shoes",
      "adopter": null
    },
    {
      "name": "運動鞋/歐規33號/藍色",
      "price": 600,
      "id": "360-3",
      "category": "Shoes",
      "adopter": null
    },
    {
      "name": "運動手錶/黑色或藍色",
      "price": 800,
      "id": "361-1",
      "category": "Clothing/Accessory",
      "adopter": null
    },
    {
      "name": "運動鞋/歐規36號/藍色/身高125公分/36公斤",
      "price": 600,
      "id": "363-1",
      "category": "Shoes",
      "adopter": null
    },
    {
      "name": "球鞋/日規25號/黑色",
      "price": 800,
      "id": "365-1",
      "category": "Shoes",
      "adopter": null
    },
    {
      "name": "布鞋/歐規34號/紅色/魔鬼沾黏貼式，不要鞋帶的",
      "price": 600,
      "id": "365-2",
      "category": "Shoes",
      "adopter": null
    },
    {
      "name": "連身嬰兒衣/粉紅/無圖案/厚棉/90cm/8kg/",
      "price": 600,
      "id": "365-3",
      "category": "Clothing/Accessory",
      "adopter": null
    },
    {
      "name": "手錶/白色/錶面空白(不要有圖案)",
      "price": 600,
      "id": "367-1",
      "category": "Clothing/Accessory",
      "adopter": null
    },
    {
      "name": "手錶(指針式)/銀色",
      "price": 1000,
      "id": "369-1",
      "category": "Clothing/Accessory",
      "adopter": null
    },
    {
      "name": "手錶(指針式)/黑色",
      "price": 800,
      "id": "369-2",
      "category": "Clothing/Accessory",
      "adopter": null
    },
    {
      "name": "涼鞋/歐規43號",
      "price": 600,
      "id": "371-1",
      "category": "Shoes",
      "adopter": null
    },
    {
      "name": "水彩畫筆畫具",
      "price": 800,
      "id": "372-1",
      "category": "Stationery",
      "adopter": null
    },
    {
      "name": "布鞋/日規24號/黑色",
      "price": 600,
      "id": "372-2",
      "category": "Shoes",
      "adopter": null
    },
    {
      "name": "布鞋/日規23號/黑色",
      "price": 600,
      "id": "372-3",
      "category": "Shoes",
      "adopter": null
    },
    {
      "name": "0.38原子筆組",
      "price": 1000,
      "id": "56-2",
      "category": "Stationery",
      "adopter": null
    },
    {
      "name": "素描繪本組",
      "price": 1000,
      "id": "56-3",
      "category": "Miscellaneous",
      "adopter": null
    },
    {
      "name": "金石堂禮券1000元",
      "price": 1000,
      "id": "120-3",
      "category": "Gift Cards",
      "adopter": null
    },
    {
      "name": "高筒運動鞋/日規29號/藍色 (一定要高筒\r)",
      "price": 1000,
      "id": "165-2",
      "category": "Shoes",
      "adopter": null
    },
    {
      "name": "運動鞋/日規23.5號/黑色",
      "price": 800,
      "id": "165-3",
      "category": "Shoes",
      "adopter": null
    },
    {
      "name": "金石堂禮券1200元",
      "price": 1200,
      "id": "175-2",
      "category": "Gift Cards",
      "adopter": null
    },
    {
      "name": "金石堂禮券1000元",
      "price": 1000,
      "id": "175-3",
      "category": "Gift Cards",
      "adopter": null
    },
    {
      "name": "誠品禮券1000元",
      "price": 1000,
      "id": "203-1",
      "category": "Gift Cards",
      "adopter": null
    },
    {
      "name": "遙控坦克車 或 遙控汽車",
      "price": 600,
      "id": "203-2",
      "category": "Miscellaneous",
      "adopter": null
    },
    {
      "name": "後背包/黑色/素面不要圖案",
      "price": 1000,
      "id": "209-1",
      "category": "Miscellaneous",
      "adopter": null
    },
    {
      "name": "誠品禮券1000元",
      "price": 1000,
      "id": "227-1",
      "category": "Gift Cards",
      "adopter": null
    },
    {
      "name": "誠品禮券800元",
      "price": 800,
      "id": "227-2",
      "category": "Gift Cards",
      "adopter": null
    },
    {
      "name": "運動鞋/日規24號/紅色",
      "price": 800,
      "id": "244-1",
      "category": "Shoes",
      "adopter": null
    },
    {
      "name": "誠品禮券1200元",
      "price": 1200,
      "id": "251-1",
      "category": "Gift Cards",
      "adopter": null
    },
    {
      "name": "誠品禮券1000元",
      "price": 1000,
      "id": "251-2",
      "category": "Gift Cards",
      "adopter": null
    },
    {
      "name": "XXXL運動長褲/160CM 78KG",
      "price": 1000,
      "id": "273-1",
      "category": "Clothing/Accessory",
      "adopter": null
    },
    {
      "name": "益智遊戲",
      "price": 600,
      "id": "273-2",
      "category": "Miscellaneous",
      "adopter": null
    },
    {
      "name": "誠品禮券1000元",
      "price": 1000,
      "id": "292-1",
      "category": "Gift Cards",
      "adopter": null
    },
    {
      "name": "誠品禮券800元",
      "price": 800,
      "id": "292-2",
      "category": "Gift Cards",
      "adopter": null
    },
    {
      "name": "誠品禮券600元",
      "price": 600,
      "id": "292-3",
      "category": "Gift Cards",
      "adopter": null
    },
    {
      "name": "誠品禮券600元",
      "price": 600,
      "id": "292-4",
      "category": "Gift Cards",
      "adopter": null
    },
    {
      "name": "金石堂禮券600元",
      "price": 600,
      "id": "300-1",
      "category": "Gift Cards",
      "adopter": null
    },
    {
      "name": "運動鞋/歐規38號/黑色",
      "price": 1000,
      "id": "316-1",
      "category": "Shoes",
      "adopter": null
    },
    {
      "name": "運動鞋/歐規38號/白色",
      "price": 1000,
      "id": "316-2",
      "category": "Shoes",
      "adopter": null
    },
    {
      "name": "卡通手錶(電子)",
      "price": 600,
      "id": "348-1",
      "category": "Clothing/Accessory",
      "adopter": null
    },
    {
      "name": "學齡前益智遊戲",
      "price": 600,
      "id": "357-1",
      "category": "Miscellaneous",
      "adopter": null
    },
    {
      "name": "保溫瓶/0.36L/黑色",
      "price": 800,
      "id": "366-1",
      "category": "Miscellaneous",
      "adopter": null
    },
    {
      "name": "運動鞋/歐規44.5號/黑色",
      "price": 800,
      "id": "370-1",
      "category": "Shoes",
      "adopter": null
    }
  ]
}